[{"type":"tab","id":"59620763.a69df8","label":"Sheet 1"},{"id":"5a24f519.a5db0c","type":"mqtt-broker","z":"59620763.a69df8","broker":"api.servioticy.com","port":"1883","clientid":"","usetls":false,"verifyservercert":true,"compatmode":true,"keepalive":"15","cleansession":true,"willTopic":"","willQos":"0","willRetain":"false","willPayload":"","birthTopic":"","birthQos":"0","birthRetain":"false","birthPayload":""},{"id":"ac0f9b6b.53f068","type":"mqtt in","z":"59620763.a69df8","name":"Photocell subscription","topic":"YjgzNDJkOTItMjBhNy00NmVhLTk1OGYtMzFlYzliMzFkZDI3NWNkNzEwODUtZDhmYS00MjgyLWFjNWEtMDI4OWI1MGU0Zjcy/14471106533281c48f919229c4092859b52ad68c43ebe/streams/status/updates","broker":"5a24f519.a5db0c","x":170,"y":102,"wires":[["ca91dc57.356e2"]]},{"id":"213e7925.dec186","type":"mqtt in","z":"59620763.a69df8","name":"Receive AC actuations","topic":"144711066218781ff71a0140e42e9be87ee78b3ed0d90/actions","broker":"5a24f519.a5db0c","x":176,"y":785,"wires":[["6bfad7d9.940528"]]},{"id":"6bfad7d9.940528","type":"debug","z":"59620763.a69df8","name":"","active":false,"console":"false","complete":"false","x":447,"y":787,"wires":[]},{"id":"ca91dc57.356e2","type":"debug","z":"59620763.a69df8","name":"","active":true,"console":"false","complete":"false","x":422,"y":101,"wires":[]},{"id":"ce02c971.31fd38","type":"mqtt in","z":"59620763.a69df8","name":"Humiditysensor subscription","topic":"YjgzNDJkOTItMjBhNy00NmVhLTk1OGYtMzFlYzliMzFkZDI3NWNkNzEwODUtZDhmYS00MjgyLWFjNWEtMDI4OWI1MGU0Zjcy/14471106555005e3e8190c81144018d75ed28cd1b36ee/streams/status/updates","broker":"5a24f519.a5db0c","x":181,"y":178,"wires":[["4896aba4.b76954"]]},{"id":"4896aba4.b76954","type":"debug","z":"59620763.a69df8","name":"","active":true,"console":"false","complete":"false","x":427,"y":177,"wires":[]},{"id":"6d2117e6.92dee8","type":"function","z":"59620763.a69df8","name":"transform","func":"ret = {\n    'status': msg.payload.channels.temperature[\"current-value\"] > 30\n}\nmsg.headers =  {\n        \"Content-type\" : \"text/plain\",\n        \"Authorization\": \"YjgzNDJkOTItMjBhNy00NmVhLTk1OGYtMzFlYzliMzFkZDI3NWNkNzEwODUtZDhmYS00MjgyLWFjNWEtMDI4OWI1MGU0Zjcy\"\n    }\nmsg.payload = ret\nreturn msg;","outputs":1,"noerr":0,"x":168,"y":491,"wires":[["dd36ae7c.22c95","c09b5dbf.3f64a"]]},{"id":"fe268e29.01d97","type":"mqtt in","z":"59620763.a69df8","name":"Receive blind actuations","topic":"1447110660004abedf639d15a464796eecaac0a76525e/actions","broker":"5a24f519.a5db0c","x":175,"y":698,"wires":[["b6596c4c.49a69"]]},{"id":"b6596c4c.49a69","type":"debug","z":"59620763.a69df8","name":"","active":true,"console":"false","complete":"false","x":438,"y":703,"wires":[]},{"id":"f6297b5d.09d688","type":"mqtt in","z":"59620763.a69df8","name":"Tempsensor subscription","topic":"YjgzNDJkOTItMjBhNy00NmVhLTk1OGYtMzFlYzliMzFkZDI3NWNkNzEwODUtZDhmYS00MjgyLWFjNWEtMDI4OWI1MGU0Zjcy/1447110657631eda41f6cfe2440b4806bb6c83a60991d/streams/status/updates","broker":"5a24f519.a5db0c","x":177,"y":257,"wires":[["2dc8263c.d237da","9fa9b433.605648"]]},{"id":"2dc8263c.d237da","type":"debug","z":"59620763.a69df8","name":"","active":true,"console":"false","complete":"false","x":421,"y":256,"wires":[]},{"id":"9fa9b433.605648","type":"json","z":"59620763.a69df8","name":"","x":166,"y":389,"wires":[["6d2117e6.92dee8"]]},{"id":"dd36ae7c.22c95","type":"http request","z":"59620763.a69df8","name":"Send blind actuation","method":"POST","ret":"txt","url":"http://api.servioticy.com/1447110660004abedf639d15a464796eecaac0a76525e/actuations/blindstatus","x":443,"y":413,"wires":[["fd20b682.02df48"]]},{"id":"fd20b682.02df48","type":"debug","z":"59620763.a69df8","name":"","active":true,"console":"false","complete":"false","x":653,"y":409,"wires":[]},{"id":"c09b5dbf.3f64a","type":"http request","z":"59620763.a69df8","name":"Send AC actuation","method":"POST","ret":"txt","url":"http://api.servioticy.com/144711066218781ff71a0140e42e9be87ee78b3ed0d90/actuations/aaccstatus","x":448,"y":528,"wires":[["6a3d4a4b.95c2b4"]]},{"id":"6a3d4a4b.95c2b4","type":"debug","z":"59620763.a69df8","name":"","active":true,"console":"false","complete":"false","x":658,"y":524,"wires":[]}]